teev/__init__.py
teev/app.py
teev/default_settings.py
teev/errors.py
teev/keyboard.py
teev/log.py
teev/tests/__init__.py
teev/tests/keyboard.py
teev-0.0.1.dev1.dist-info/AUTHORS
teev-0.0.1.dev1.dist-info/LICENSE
teev-0.0.1.dev1.dist-info/METADATA
teev-0.0.1.dev1.dist-info/WHEEL
teev-0.0.1.dev1.dist-info/top_level.txt
teev-0.0.1.dev1.dist-info/RECORD
