Metadata-Version: 2.1
Name: teev
Version: 0.0.1.dev1
Summary: Asynchronous Telegram Bot Framework.
Home-page: http://teev.startech.live
Author: Stepan Starovoitov
Author-email: stepan@startech.live
License: BSD
Project-URL: Documentation, http://teev.startech.live
Project-URL: Code, https://github.com/startech-live/teev
Project-URL: Issue tracker, https://github.com/startech-live/teev/issues
Platform: any
Classifier: Development Status :: 5 - Production/Stable
Classifier: Environment :: Web Environment
Classifier: Intended Audience :: Developers
Classifier: License :: OSI Approved :: BSD License
Classifier: Operating System :: OS Independent
Classifier: Programming Language :: Python
Classifier: Programming Language :: Python :: 3.8
Classifier: Programming Language :: Python :: 3.9
Classifier: Programming Language :: Python :: 3.10
Classifier: Topic :: Internet :: WWW/HTTP :: Dynamic Content
Classifier: Topic :: Software Development :: Libraries :: Application Frameworks
Classifier: Topic :: Software Development :: Libraries :: Python Modules
Requires-Python: >=3.8
Requires-Dist: aiogram
Requires-Dist: flask
Provides-Extra: dev
Requires-Dist: alabaster ; extra == 'dev'
Requires-Dist: doc8 ; extra == 'dev'
Requires-Dist: pytest ; extra == 'dev'
Requires-Dist: sphinx ; extra == 'dev'
Requires-Dist: testfixtures ; extra == 'dev'
Requires-Dist: tox ; extra == 'dev'
Provides-Extra: docs
Requires-Dist: alabaster ; extra == 'docs'
Requires-Dist: doc8 ; extra == 'docs'
Requires-Dist: sphinx ; extra == 'docs'
Provides-Extra: tests
Requires-Dist: pytest ; extra == 'tests'
Requires-Dist: testfixtures ; extra == 'tests'
Requires-Dist: tox ; extra == 'tests'
